__init__.py
core.py
numeric.py
symbolic.py
utils.py
eigenfind-0.1.0.dist-info/licenses/LICENSE
eigenfind-0.1.0.dist-info/METADATA
eigenfind-0.1.0.dist-info/WHEEL
eigenfind-0.1.0.dist-info/top_level.txt
eigenfind-0.1.0.dist-info/RECORD
