Metadata-Version: 2.4
Name: eigenfind
Version: 0.1.0
Summary: A Python library to find eigenvectors by known eigenvalues.
Author-email: Aleks Mashanski <maszanski@yahoo.com>
License: MIT
Project-URL: Homepage, https://github.com/metroproxyn/eigenfind
Project-URL: Documentation, https://github.com/metroproxyn/eigenfind/blob/master/README.md
Project-URL: Source, https://github.com/yourusername/eigenfind
Keywords: eigenvectors,eigenvalues,linear algebra,math,numpy,scipy
Classifier: Development Status :: 3 - Alpha
Classifier: Intended Audience :: Science/Research
Classifier: License :: OSI Approved :: MIT License
Classifier: Programming Language :: Python :: 3
Classifier: Topic :: Scientific/Engineering :: Mathematics
Requires-Python: >=3.8
License-File: LICENSE
Dynamic: license-file
